[
  {
    "ClassName": "Game.Gameplay.Meta.Skins.ProjectileCollection",
    "Fields": [
      {
        "Name": "BoughtSkins",
        "Value": "[\"Bolt\"]",
        "Type": "System.Collections.Generic.List`1[System.String]",
        "Metadata": {
          "PrettyName": "Undefined attribute name",
          "MinValue": "NaN",
          "MaxValue": "NaN",
          "ValidOptions": null
        }
      },
      {
        "Name": "SelectedSkin",
        "Value": "Bolt",
        "Type": "System.String",
        "Metadata": {
          "PrettyName": "Undefined attribute name",
          "MinValue": "NaN",
          "MaxValue": "NaN",
          "ValidOptions": null
        }
      }
    ]
  },
  {
    "ClassName": "Game.Gameplay.Meta.Curencies.CurenciesContext",
    "Fields": [
      {
        "Name": "CommonCoins",
        "Value": "6069",
        "Type": "System.Numerics.BigInteger",
        "Metadata": {
          "PrettyName": "Undefined attribute name",
          "MinValue": "NaN",
          "MaxValue": "NaN",
          "ValidOptions": null
        }
      },
      {
        "Name": "SkinTokens",
        "Value": "14",
        "Type": "System.Numerics.BigInteger",
        "Metadata": {
          "PrettyName": "Undefined attribute name",
          "MinValue": "NaN",
          "MaxValue": "NaN",
          "ValidOptions": null
        }
      },
      {
        "Name": "LifetimeSpending",
        "Value": "3750",
        "Type": "System.Numerics.BigInteger",
        "Metadata": {
          "PrettyName": "Undefined attribute name",
          "MinValue": "NaN",
          "MaxValue": "NaN",
          "ValidOptions": null
        }
      }
    ]
  },
  {
    "ClassName": "Game.Gameplay.Meta.UpgradeSystem.UpgradeContext",
    "Fields": [
      {
        "Name": "CrossbowLevel",
        "Value": "4",
        "Type": "System.Int32",
        "Metadata": {
          "PrettyName": "Undefined attribute name",
          "MinValue": "NaN",
          "MaxValue": "NaN",
          "ValidOptions": null
        }
      },
      {
        "Name": "ArrowLevel",
        "Value": "2",
        "Type": "System.Int32",
        "Metadata": {
          "PrettyName": "Undefined attribute name",
          "MinValue": "NaN",
          "MaxValue": "NaN",
          "ValidOptions": null
        }
      },
      {
        "Name": "InitialArrowCount",
        "Value": "1",
        "Type": "System.Int32",
        "Metadata": {
          "PrettyName": "Undefined attribute name",
          "MinValue": "NaN",
          "MaxValue": "NaN",
          "ValidOptions": null
        }
      },
      {
        "Name": "PassiveIncome",
        "Value": "1",
        "Type": "System.Int32",
        "Metadata": {
          "PrettyName": "Undefined attribute name",
          "MinValue": "NaN",
          "MaxValue": "NaN",
          "ValidOptions": null
        }
      }
    ]
  },
  {
    "ClassName": "Game.Gameplay.Meta.Skins.ProjectileSkinCollection",
    "Fields": [
      {
        "Name": "SelectedSkin",
        "Value": "Arrow",
        "Type": "System.String",
        "Metadata": {
          "PrettyName": "Undefined attribute name",
          "MinValue": "NaN",
          "MaxValue": "NaN",
          "ValidOptions": null
        }
      },
      {
        "Name": "BoughtSkins",
        "Value": "[\"Bolt\",\"Arrow\"]",
        "Type": "System.Collections.Generic.List`1[System.String]",
        "Metadata": {
          "PrettyName": "Undefined attribute name",
          "MinValue": "NaN",
          "MaxValue": "NaN",
          "ValidOptions": null
        }
      }
    ]
  },
  {
    "ClassName": "Game.Gameplay.Meta.Skins.CrossbowSkinCollection",
    "Fields": [
      {
        "Name": "BoughtSkins",
        "Value": "[\"Wood\",\"RedWood\"]",
        "Type": "System.Collections.Generic.List`1[System.String]",
        "Metadata": {
          "PrettyName": "Undefined attribute name",
          "MinValue": "NaN",
          "MaxValue": "NaN",
          "ValidOptions": null
        }
      },
      {
        "Name": "SelectedSkin",
        "Value": "RedWood",
        "Type": "System.String",
        "Metadata": {
          "PrettyName": "Undefined attribute name",
          "MinValue": "NaN",
          "MaxValue": "NaN",
          "ValidOptions": null
        }
      }
    ]
  }
]